modular_conf/__init__.py
modular_conf/fields.py
modular_conf/tests/__init__.py
modular_conf-0.2.dist-info/LICENSE
modular_conf-0.2.dist-info/METADATA
modular_conf-0.2.dist-info/WHEEL
modular_conf-0.2.dist-info/top_level.txt
modular_conf-0.2.dist-info/RECORD
