Metadata-Version: 2.1
Name: modular-conf
Version: 0.2
Summary: A modular python configuration utility
Home-page: http://github.com/mikonse/modular_conf
Author: Michael Loipfuehrer
Author-email: 
License: MIT
Platform: UNKNOWN
Classifier: Programming Language :: Python :: 3
Classifier: License :: OSI Approved :: MIT License
Classifier: Operating System :: OS Independent
